zerocue/__init__.py
zerocue-0.3.0.dist-info/LICENSE
zerocue-0.3.0.dist-info/METADATA
zerocue-0.3.0.dist-info/WHEEL
zerocue-0.3.0.dist-info/entry_points.txt
zerocue-0.3.0.dist-info/top_level.txt
zerocue-0.3.0.dist-info/zip-safe
zerocue-0.3.0.dist-info/RECORD
