Metadata-Version: 2.1
Name: zerocue
Version: 0.3.0
Summary: Remove first INDEX track time from every following INDEXes in a CUE sheet file
Home-page: https://github.com/shaftoe/zerocue
Author: Alexander Fortin
License: UNKNOWN
Keywords: cue,cuesheets,cue-sheets,audio
Platform: UNKNOWN
Classifier: Development Status :: 5 - Production/Stable
Classifier: Environment :: Console
Classifier: License :: OSI Approved :: Apache Software License
Classifier: Operating System :: OS Independent
Classifier: Programming Language :: Python :: 3
Classifier: Topic :: Text Processing :: Filters
Classifier: Topic :: Multimedia :: Sound/Audio
Requires-Python: >=3.8
